LICENSE.txt
MANIFEST.in
README.rst
setup.py
docs/doubles.rst
docs/index.rst
duplo/__init__.py
duplo/doubles.py
duplo/six.py
duplo.egg-info/PKG-INFO
duplo.egg-info/SOURCES.txt
duplo.egg-info/dependency_links.txt
duplo.egg-info/top_level.txt