Metadata-Version: 1.0
Name: duplo
Version: 1.0.3
Summary: Makes testing easier
Home-page: https://github.com/jdunck/duplo
Author: Jeremy Dunck
Author-email: jdunck@gmail.com
License: UNKNOWN
Platform: UNKNOWN
